acsaver/__init__.py
acsaver/__main__.py
acsaver/article.py
acsaver/bangumi.py
acsaver/live.py
acsaver/moment.py
acsaver/saver.py
acsaver/templates/anime.html
acsaver/templates/article.html
acsaver/templates/bangumi.html
acsaver/templates/feed.html
acsaver/templates/index.html
acsaver/templates/moment.html
acsaver/templates/part/feed_nav.html
acsaver/templates/part/main.html
acsaver/templates/part/main_footer.html
acsaver/templates/part/main_header.html
acsaver/templates/part/main_toolbar.html
acsaver/templates/video.html
acsaver/utils/__init__.py
acsaver/utils/ffmpeg_progress_yield.py
acsaver/utils/source.py
acsaver/utils/utils.py
acsaver/video.py
acsaver-0.1.5.dist-info/entry_points.txt
acsaver-0.1.5.dist-info/LICENSE
acsaver-0.1.5.dist-info/WHEEL
acsaver-0.1.5.dist-info/METADATA
acsaver-0.1.5.dist-info/RECORD
