Metadata-Version: 2.1
Name: acsaver
Version: 0.1.5
Summary: acfunsdk - AcSaver
Home-page: https://pypi.org/project/acsaver/
License: MIT
Keywords: acfun,sdk,acfunsdk,unofficeical,acsaver
Author: dolacmeo
Author-email: dolacmeo@gmail.com
Requires-Python: >=3.8,<4.0
Classifier: Development Status :: 1 - Planning
Classifier: Environment :: Console
Classifier: Intended Audience :: Developers
Classifier: License :: OSI Approved :: MIT License
Classifier: Natural Language :: Chinese (Simplified)
Classifier: Natural Language :: English
Classifier: Operating System :: Microsoft :: Windows
Classifier: Operating System :: Microsoft :: Windows :: Windows 10
Classifier: Programming Language :: JavaScript
Classifier: Programming Language :: Python :: 3
Classifier: Programming Language :: Python :: 3.8
Classifier: Programming Language :: Python :: 3.9
Classifier: Programming Language :: Python :: 3.10
Classifier: Programming Language :: Python :: 3
Classifier: Programming Language :: Python :: 3.8
Classifier: Programming Language :: Python :: 3.9
Classifier: Topic :: Education
Classifier: Topic :: Internet :: WWW/HTTP :: Browsers
Classifier: Topic :: Software Development :: Libraries
Requires-Dist: acfunsdk (>=0.9.5,<0.10.0)
Requires-Dist: click (>=8.1,<9.0)
Requires-Dist: filetype (>=1.1,<2.0)
Requires-Dist: jinja2 (>=3.1,<4.0)
Requires-Dist: pillow (>=9,<10)
Requires-Dist: rich (>=12.5,<13.0)
Project-URL: Bug Tracker, https://github.com/dolaCmeo/acsaver/issues
Project-URL: Documentation, https://github.com/dolaCmeo/acsaver
Project-URL: Repository, https://github.com/dolaCmeo/acsaver
